LICENSE.md
MANIFEST.in
README.md
README.rst
fastentrypoints.py
setup.cfg
setup.py
devxhub/__init__.py
devxhub/argument_parser.py
devxhub/conf.py
devxhub/const.py
devxhub/corrector.py
devxhub/exceptions.py
devxhub/logs.py
devxhub/types.py
devxhub/ui.py
devxhub/utils.py
devxhub.egg-info/PKG-INFO
devxhub.egg-info/SOURCES.txt
devxhub.egg-info/dependency_links.txt
devxhub.egg-info/entry_points.txt
devxhub.egg-info/not-zip-safe
devxhub.egg-info/requires.txt
devxhub.egg-info/top_level.txt
devxhub/entrypoints/__init__.py
devxhub/entrypoints/alias.py
devxhub/entrypoints/fix_command.py
devxhub/entrypoints/main.py
devxhub/entrypoints/not_configured.py
devxhub/entrypoints/shell_logger.py
devxhub/output_readers/__init__.py
devxhub/output_readers/read_log.py
devxhub/output_readers/rerun.py
devxhub/output_readers/shell_logger.py
devxhub/rules/__init__.py
devxhub/rules/adb_unknown_command.py
devxhub/rules/ag_literal.py
devxhub/rules/apt_get.py
devxhub/rules/apt_get_search.py
devxhub/rules/apt_invalid_operation.py
devxhub/rules/apt_list_upgradable.py
devxhub/rules/apt_upgrade.py
devxhub/rules/aws_cli.py
devxhub/rules/az_cli.py
devxhub/rules/brew_cask_dependency.py
devxhub/rules/brew_install.py
devxhub/rules/brew_link.py
devxhub/rules/brew_reinstall.py
devxhub/rules/brew_uninstall.py
devxhub/rules/brew_unknown_command.py
devxhub/rules/brew_update_formula.py
devxhub/rules/cargo.py
devxhub/rules/cargo_no_command.py
devxhub/rules/cat_dir.py
devxhub/rules/cd_correction.py
devxhub/rules/cd_cs.py
devxhub/rules/cd_mkdir.py
devxhub/rules/cd_parent.py
devxhub/rules/chmod_x.py
devxhub/rules/choco_install.py
devxhub/rules/composer_not_command.py
devxhub/rules/conda_mistype.py
devxhub/rules/cp_create_destination.py
devxhub/rules/cp_omitting_directory.py
devxhub/rules/cpp11.py
devxhub/rules/dirty_untar.py
devxhub/rules/dirty_unzip.py
devxhub/rules/django_south_ghost.py
devxhub/rules/django_south_merge.py
devxhub/rules/dnf_no_such_command.py
devxhub/rules/docker_image_being_used_by_container.py
devxhub/rules/docker_login.py
devxhub/rules/docker_not_command.py
devxhub/rules/dry.py
devxhub/rules/fab_command_not_found.py
devxhub/rules/fix_alt_space.py
devxhub/rules/fix_file.py
devxhub/rules/gem_unknown_command.py
