Metadata-Version: 2.1
Name: devxhub
Version: 3.33.0
Summary: Magnificent app which corrects your previous console command
Home-page: https://github.com/git-foysal-1/devxhub-terminal
Author: DEVXHUB
Author-email: foysal.devxhub@gmail.com
License: MIT
Platform: UNKNOWN
License-File: LICENSE.md
